ceda_cc/__init__.py
ceda_cc/amap2nco.py
ceda_cc/c4.py
ceda_cc/c4_run.py
ceda_cc/ccinit.py
ceda_cc/checkT.py
ceda_cc/comp_mip.py
ceda_cc/extractMipInfo.py
ceda_cc/fcc_utils.py
ceda_cc/fcc_utils2.py
ceda_cc/file_utils.py
ceda_cc/ncq3.py
ceda_cc/summary.py
ceda_cc/summary_by_error_code.py
ceda_cc/unitTestsS1.py
ceda_cc/unitTestsS2.py
ceda_cc/utils_c4.py
ceda_cc/versionConfig.py
ceda_cc/xceptions.py
ceda_cc/ceda_cc_config/__init__.py
ceda_cc/ceda_cc_config/__init__.pyc
ceda_cc/ceda_cc_config/config_c4.py
ceda_cc/ceda_cc_config/config_c4.pyc
ceda_cc/ceda_cc_config/utils_config.py
ceda_cc/ceda_cc_config/utils_config.pyc
ceda_cc/ceda_cc_config/__pycache__/__init__.cpython-38.pyc
ceda_cc/ceda_cc_config/__pycache__/config_c4.cpython-38.pyc
ceda_cc/ceda_cc_config/__pycache__/utils_config.cpython-38.pyc
ceda_cc/ceda_cc_config/config/canonicalVariations.txt
ceda_cc/ceda_cc_config/config/import_ccmi2022.sh
ceda_cc/ceda_cc_config/config/table_imports.py
ceda_cc/ceda_cc_config/config/testStandardNames.txt
ceda_cc/ceda_cc_config/config/__pycache__/table_imports.cpython-38.pyc
ceda_cc/ceda_cc_config/config/ccmi2022/Tables/CCMI2022_A10dayPt.json
ceda_cc/ceda_cc_config/config/ccmi2022/Tables/CCMI2022_Aday.json
ceda_cc/ceda_cc_config/config/ccmi2022/Tables/CCMI2022_AdayZ.json
ceda_cc/ceda_cc_config/config/ccmi2022/Tables/CCMI2022_Amon.json
ceda_cc/ceda_cc_config/config/ccmi2022/Tables/CCMI2022_AmonZ.json
ceda_cc/ceda_cc_config/config/ccmi2022/Tables/CCMI2022_CV.json
ceda_cc/ceda_cc_config/config/ccmi2022/Tables/CCMI2022_coordinate.json
ceda_cc/ceda_cc_config/config/ccmi2022/Tables/CCMI2022_formula_terms.json
ceda_cc/ceda_cc_config/config/ccmi2022/Tables/CCMI2022_fx.json
ceda_cc/ceda_cc_config/config/ccmi2022/Tables/CCMI2022_grids.json
ceda_cc/ceda_cc_config/config/ccmi_vocabs/ccmi_elist.txt
ceda_cc/ceda_cc_config/config/ccmi_vocabs/ccmi_experiments.txt
ceda_cc/ceda_cc_config/config/ccmi_vocabs/globalAts.txt
ceda_cc/ceda_cc_config/config/ccmi_vocabs/models.txt
ceda_cc-1.9.2.dist-info/LICENSE
ceda_cc-1.9.2.dist-info/METADATA
ceda_cc-1.9.2.dist-info/WHEEL
ceda_cc-1.9.2.dist-info/entry_points.txt
ceda_cc-1.9.2.dist-info/top_level.txt
ceda_cc-1.9.2.dist-info/RECORD
