Metadata-Version: 2.1
Name: ceda-cc
Version: 1.9.2
Summary: CEDA Conformance Checker
Home-page: https://github.com/cedadev/ceda-cc
Author: Martin Juckes
Author-email: Martin.Juckes@stfc.ac.uk
License: BSD
Platform: UNKNOWN
Classifier: Development Status :: 5 - Production/Stable
Classifier: License :: OSI Approved :: BSD License
Classifier: Topic :: Scientific/Engineering
Classifier: Programming Language :: Python :: 3
